experiment_server/__init__.py
experiment_server/_api.py
experiment_server/_client.py
experiment_server/_participant_ordering.py
experiment_server/_process_config.py
experiment_server/_server.py
experiment_server/cli.py
experiment_server/static/css/bootstrap-5.2.3.min.css
experiment_server/static/index.html
experiment_server/static/initconfig.html
experiment_server/static/js/alpinejs3.min.js
experiment_server/static/js/bootstrap-4.5.0.min.js
experiment_server/static/js/fontawesome-1e694dd391.js
experiment_server/static/js/htmx-1.9.10.js
experiment_server/static/js/jquery-3.5.1.min.js
experiment_server/static/js/popper-1.16.0.min.js
experiment_server/static/js/sweetalert2-11.js
experiment_server/utils.py
experiment_server-0.3.6.dist-info/entry_points.txt
experiment_server-0.3.6.dist-info/LICENSE.md
experiment_server-0.3.6.dist-info/METADATA
experiment_server-0.3.6.dist-info/WHEEL
experiment_server-0.3.6.dist-info/RECORD
