Metadata-Version: 2.3
Name: experiment_server
Version: 0.3.6
Summary: Server for experiments to get configuarations from
License: MIT
Keywords: experiment,study-design
Author: Ahmed Shariff
Author-email: shariff.mfa@outlook.com
Requires-Python: >=3.8
Classifier: Development Status :: 1 - Planning
Classifier: License :: OSI Approved :: MIT License
Classifier: Natural Language :: English
Classifier: Operating System :: OS Independent
Classifier: Programming Language :: Python
Classifier: Programming Language :: Python :: 3
Classifier: Programming Language :: Python :: 3.8
Classifier: Programming Language :: Python :: 3.9
Classifier: Programming Language :: Python :: 3.10
Classifier: Programming Language :: Python :: 3.11
Classifier: Programming Language :: Python :: 3.12
Classifier: Programming Language :: Python :: 3.13
Requires-Dist: Jinja2 (>=3.1.2)
Requires-Dist: asyncio (>=3.4.3)
Requires-Dist: click (>=6.0)
Requires-Dist: click-aliases (>=1.0.4)
Requires-Dist: easydict (>=1)
Requires-Dist: importlib-metadata (>=6.8.0)
Requires-Dist: loguru (>=0.5,<0.6)
Requires-Dist: pandas (>=1)
Requires-Dist: requests (>=2.25.1)
Requires-Dist: tabulate (>=0.8.9)
Requires-Dist: toml (>=0.10.2)
Requires-Dist: tornado (>=6.2)
Requires-Dist: watchdog (>=2.1.9)
Project-URL: Documentation, https://shariff-faleel.com/experiment_server/documentation/
Project-URL: Homepage, https://shariff-faleel.com/experiment_server/
Project-URL: Repository, https://github.com/ahmed-shariff/experiment_server
